networktoolkit/__init__.py
networktoolkit/arpspoof.py
networktoolkit/dnsspoof.py
networktoolkit/netwatch.py
networktoolkit/networkscan.py
networktoolkit/portuselookup.py
networktoolkit/showhosts.py
networktoolkit/vendorlookup.py
networktoolkit-0.1.6.dist-info/entry_points.txt
networktoolkit-0.1.6.dist-info/LICENSE
networktoolkit-0.1.6.dist-info/WHEEL
networktoolkit-0.1.6.dist-info/METADATA
networktoolkit-0.1.6.dist-info/RECORD
