Metadata-Version: 2.1
Name: networktoolkit
Version: 0.1.6
Summary: A collection of networking tools
Home-page: https://github.com/mokytis/networktoolkit
License: MIT
Author: Luke Spademan
Author-email: info@lukespademan.com
Requires-Python: >=3.8,<4.0
Classifier: License :: OSI Approved :: MIT License
Classifier: Programming Language :: Python :: 3
Classifier: Programming Language :: Python :: 3.8
Classifier: Programming Language :: Python :: 3.9
Provides-Extra: docs
Requires-Dist: Click (>=7.0,<8.0)
Requires-Dist: cryptography (>=3.4.7,<4.0.0)
Requires-Dist: requests (>=2.23.0,<3.0.0)
Requires-Dist: scapy (>=2.4.3,<3.0.0)
Requires-Dist: sphinx (>=3,<4); extra == "docs"
Project-URL: Repository, https://github.com/mokytis/networktoolkit
